pymsod/__init__.py
pymsod/find_onedrive_paths.py
pymsod-0.1.6.dist-info/LICENSE
pymsod-0.1.6.dist-info/METADATA
pymsod-0.1.6.dist-info/WHEEL
pymsod-0.1.6.dist-info/RECORD
