Metadata-Version: 2.3
Name: pymsod
Version: 0.1.6
Summary: Automatically detects the location of OneDrive folders and returns its parent location
License: GNU 3.0
Author: Dominik Braun
Author-email: dome.braun@fau.de
Requires-Python: >=3.11,<4.0
Classifier: License :: Other/Proprietary License
Classifier: Programming Language :: Python :: 3
Classifier: Programming Language :: Python :: 3.11
Classifier: Programming Language :: Python :: 3.12
Classifier: Programming Language :: Python :: 3.13
Requires-Dist: aenum (>=3.1.15,<4.0.0)
